tsbase/combine.py
tsbase/ensemble.py
tsbase/metrics.py
tsbase/model.py
tsbase/preprocess.py
tsbase/sk_model.py
tsbase/torch_utils.py
tsbase/tune.py
tsbase/utils.py
tsbase/visualize.py
tsbase-1.0.3.dist-info/LICENSE
tsbase-1.0.3.dist-info/METADATA
tsbase-1.0.3.dist-info/WHEEL
tsbase-1.0.3.dist-info/top_level.txt
tsbase-1.0.3.dist-info/RECORD
